Metadata-Version: 1.2
Name: jklwcs
Version: 1.9
Summary: jike project
Home-page: https://github.com/users/Melting889/projects
Maintainer: Jike Data Analysis Modeling Group
Maintainer-email: liubingfeng@clickwifi.net
License: MIT License
Platform: UNKNOWN
